Metadata-Version: 1.0
Name: ankify
Version: 0.0.2
Summary: Tiny CLI to convert my personal notes to Anki-importable CSVs.
Home-page: UNKNOWN
Author: Harrison Mamin
Author-email: hmamin55@gmail.com
License: UNKNOWN
Platform: UNKNOWN
